marmotester
