Metadata-Version: 1.1
Name: marmo-tester
Version: 0.0.11
Summary: Marmo wallet Python SDK
Home-page: UNKNOWN
Author: Agustin Aguilar
Author-email: agusxrun@gmail.com
License: UNKNOWN
Platform: UNKNOWN
Classifier: Programming Language :: Python :: 2
Classifier: Programming Language :: Python :: 2.7
Classifier: Programming Language :: Python :: 3
Classifier: Programming Language :: Python :: 3.6
